Relukko/Relukko.py
Relukko/__init__.py
Relukko/version.py
robotframework_relukko-0.10.0.dist-info/licenses/LICENSE
robotframework_relukko-0.10.0.dist-info/WHEEL
robotframework_relukko-0.10.0.dist-info/METADATA
robotframework_relukko-0.10.0.dist-info/RECORD
