Metadata-Version: 2.4
Name: robotframework-relukko
Version: 0.10.0
Summary: Resource Locking for Robot Framework
Author-email: Reto Zingg <g.d0b3rm4n@gmail.com>
Requires-Python: >=3.12
Classifier: Development Status :: 4 - Beta
Classifier: License :: OSI Approved :: MIT License
Classifier: Framework :: Robot Framework :: Library
Classifier: Programming Language :: Python :: 3.12
Classifier: Programming Language :: Python :: 3.13
Classifier: Programming Language :: Python :: 3.14
License-File: LICENSE
Requires-Dist: requests >=2.32.5
Requires-Dist: pyrelukko >= 0.11.0
Requires-Dist: robotframework >=7.0
Project-URL: Homepage, https://gitlab.com/relukko/robotframework-relukko
Project-URL: Issues, https://gitlab.com/relukko/robotframework-relukko/-/issues
